LICENSE
MANIFEST.in
README.rst
cms.xml
setup.cfg
setup.py
./__init__.py
./cms.py
./cms.xml
./tryton.cfg
./user.py
./locale/de_DE.po
./tests/__init__.py
./tests/test_banner.py
./tests/test_cms.py
./tests/test_menuitem.py
./view/cms_article_category_form.xml
./view/cms_article_category_tree.xml
./view/cms_article_form.xml
./view/cms_article_tree.xml
./view/cms_banner_category_form.xml
./view/cms_banner_category_tree.xml
./view/cms_banner_form.xml
./view/cms_banner_tree.xml
./view/cms_menu_item_form.xml
./view/cms_menu_item_tree.xml
./view/cms_menu_item_tree2.xml
./view/cms_website_form.xml
fio_nereid_cms.egg-info/PKG-INFO
fio_nereid_cms.egg-info/SOURCES.txt
fio_nereid_cms.egg-info/dependency_links.txt
fio_nereid_cms.egg-info/entry_points.txt
fio_nereid_cms.egg-info/not-zip-safe
fio_nereid_cms.egg-info/pbr.json
fio_nereid_cms.egg-info/requires.txt
fio_nereid_cms.egg-info/top_level.txt
locale/de_DE.po